coeai/__init__.py
coeai/infer.py
coeai-3.1.0.dist-info/licenses/LICENSE
coeai-3.1.0.dist-info/METADATA
coeai-3.1.0.dist-info/WHEEL
coeai-3.1.0.dist-info/top_level.txt
coeai-3.1.0.dist-info/RECORD
